LICENSE
README.md
setup.py
specforge/__init__.py
specforge/distributed.py
specforge/lr_scheduler.py
specforge/utils.py
specforge.egg-info/PKG-INFO
specforge.egg-info/SOURCES.txt
specforge.egg-info/dependency_links.txt
specforge.egg-info/requires.txt
specforge.egg-info/top_level.txt
specforge/core/__init__.py
specforge/core/eagle3.py
specforge/data/__init__.py
specforge/data/preprocessing.py
specforge/data/template.py
specforge/data/utils.py
specforge/layers/__init__.py
specforge/layers/linear.py
specforge/modeling/__init__.py
specforge/modeling/_mask_utils.py
specforge/modeling/auto.py
specforge/modeling/utils.py
specforge/modeling/draft/__init__.py
specforge/modeling/draft/base.py
specforge/modeling/draft/llama3_eagle.py
specforge/modeling/target/__init__.py
specforge/modeling/target/base.py
specforge/modeling/target/llama4.py
specforge/modeling/target/qwen3_moe.py
specforge/modeling/target/target_head.py