Metadata-Version: 2.1
Name: specforge
Version: 0.1.0
Home-page: https://github.com/sgl-project/SpecForge
Author: SGLang Team
License-File: LICENSE
